backup_tool/__init__.py
backup_tool/__main__.py
backup_tool/backup.py
backup_tool/history.py
backup_tool/interval.py
backup_tool/main.py
backup_tool/util.py
backup_tool/providers/__init__.py
backup_tool/providers/backup/MysqldumpBackupProvider.py
backup_tool/providers/backup/PostgresqlBackupProvider.py
backup_tool/providers/backup/__init__.py
backup_tool/providers/storage/SFTPStorageProvider.py
backup_tool/providers/storage/__init__.py
backup_tool/providers/transformer/AESEncryptionTransformer.py
backup_tool/providers/transformer/__init__.py
backup_tool-0.1.0.dist-info/LICENSE
backup_tool-0.1.0.dist-info/METADATA
backup_tool-0.1.0.dist-info/WHEEL
backup_tool-0.1.0.dist-info/top_level.txt
backup_tool-0.1.0.dist-info/RECORD
