Metadata-Version: 2.1
Name: backup-tool
Version: 0.1.0
Summary: backup tool
Home-page: https://github.com/HubertBalcerzak/backup-tool
Author: Hubertus
License: UNKNOWN
Project-URL: Bug Tracker, https://github.com/HubertBalcerzak/backup-tool/issues
Platform: UNKNOWN
Classifier: Programming Language :: Python :: 3
Classifier: License :: OSI Approved :: MIT License
Requires-Python: >=3.8
Requires-Dist: pysftp (>=0.2.9)
Requires-Dist: paramiko (>=2.7.2)
Requires-Dist: psycopg2 (>=2.8.6)
